{
  "version": "3.0",
  "generated": "2025-11-06T18:20:16Z",
  "data_repo": {
    "commit": "15a9c003bc2e1357d64c794fbaf8a098f2562334",
    "commit_short": "15a9c00",
    "branch": "main",
    "commit_date": "2025-11-06T17:14:12Z",
    "dirty": true
  },
  "pipeline": {
    "gather": {
      "last_run": "2025-11-06T18:19:46Z",
      "sources": {
        "beta": {
          "last_fetch": "2025-11-06T18:19:44Z",
          "current_hash": "4c9a33d5ae208d7223a9cf0d444871b89e17ace248cdcbc4d45bcc33537c6f74",
          "previous_hash": "f19a59a358cf1489b2f55fb6b6fdf3f0f031cdddff7a2e4012e815d656c2c1af",
          "changed": true
        },
        "gdmf": {
          "last_fetch": "2025-11-06T18:19:41Z",
          "current_hash": "6fba7f2a12a18dda5a983e73c94c1c50f804d76f03f6417e209b2a97668888ad",
          "previous_hash": "6fba7f2a12a18dda5a983e73c94c1c50f804d76f03f6417e209b2a97668888ad",
          "changed": false
        },
        "ipsw": {
          "last_fetch": "2025-11-06T18:19:43Z",
          "current_hash": "43b567f61388ba98809db0b4366b83cd4e23ed9676a343775bf4dcf30716951f",
          "previous_hash": "bc32d2ec1baf87697459a754a48f5340c2d3882abdd0ce2a3899ea373870ab97",
          "changed": true
        },
        "kev": {
          "last_fetch": "2025-11-06T18:19:40Z",
          "current_hash": "5d3c5af285f536c3ab29fa4bc3250cb288d2ae21b59bfbf2610adc42e233569b",
          "previous_hash": "6fe10bb262fea3653d7e292327b53de32202933e4e485f076a5df1db4bcb0cb3",
          "changed": true
        },
        "uma": {
          "last_fetch": "2025-11-06T18:19:45Z",
          "current_hash": "8a9bb9e826f3784204e4747dbbd4f92ca1feaac2c439a8976c5bf5c2c8552673",
          "previous_hash": "8a9bb9e826f3784204e4747dbbd4f92ca1feaac2c439a8976c5bf5c2c8552673",
          "changed": false
        },
        "xprotect": {
          "last_fetch": "2025-11-06T18:19:46Z",
          "current_hash": "c071c5e16fb92ae0a33d8c8d07f0c725fb6aa507ef50d265393e12c6b74cd81d",
          "previous_hash": "c071c5e16fb92ae0a33d8c8d07f0c725fb6aa507ef50d265393e12c6b74cd81d",
          "changed": false
        }
      },
      "changes_detected": [
        "beta",
        "ipsw",
        "kev"
      ]
    },
    "fetch": {
      "last_run_start": "2025-11-06T18:19:47Z",
      "last_run_end": "2025-11-06T18:20:15Z",
      "mode": "online",
      "releases_fetched": 618,
      "current_hash": "929e32852b6ad8b0932c1c59ecf524ffb620692cbf753164ff2294105dc2bf58",
      "previous_hash": "0ef0d5ef2cf518eff7b3eb0e7fdadc1ad0ad079bf10d0feb25131f16d7fc69dc",
      "performance_stats": "21.38 releases/sec"
    },
    "build": {
      "last_run": "2025-11-06T18:20:15Z",
      "v1": {
        "last_run": "2025-11-06T18:20:15Z",
        "platforms": {
          "ios": {
            "current_hash": "5774118ee9ccf71cbfd3c7bff6da149af89f41d3a2802b43366dfc4c0c44e5c8",
            "previous_hash": null,
            "entries": 3,
            "size_bytes": 412060,
            "last_updated": "2025-11-06T18:20:15Z"
          },
          "macos": {
            "current_hash": "8fb940c5766c85ab4015eb55c322ed4456e8309f2ea3ca2e743af80a4662b8ce",
            "previous_hash": null,
            "entries": 5,
            "size_bytes": 412060,
            "last_updated": "2025-11-06T18:20:15Z"
          },
          "safari": {
            "current_hash": "992ee66f36335f6a02514a42390b3053cf8080cc5874430346dfb31c844b4864",
            "previous_hash": null,
            "entries": 3,
            "size_bytes": 412060,
            "last_updated": "2025-11-06T18:20:15Z"
          },
          "tvos": {
            "current_hash": "2e4b5c08ace61b982239a78e29e0e96cae6a17464f180b47442890bdaff75d0f",
            "previous_hash": null,
            "entries": 2,
            "size_bytes": 412060,
            "last_updated": "2025-11-06T18:20:15Z"
          },
          "visionos": {
            "current_hash": "8704cfa15ad2fcd88b260178c150bae6972860edc9d6cea0af380486feafc3c2",
            "previous_hash": null,
            "entries": 2,
            "size_bytes": 412060,
            "last_updated": "2025-11-06T18:20:15Z"
          },
          "watchos": {
            "current_hash": "2b4d1d9e69ae409df6e66f5c74c13fa68867ea9a12dedab54439ae107ac373a6",
            "previous_hash": null,
            "entries": 1,
            "size_bytes": 412060,
            "last_updated": "2025-11-06T18:20:15Z"
          }
        }
      },
      "v2": {
        "last_run": "2025-11-06T18:20:15Z",
        "platforms": {
          "ios": {
            "current_hash": "bfd7595f88a24187bf22ff6a7fe2a1963f21383dbe52f385b9a1e6ee24c3939d",
            "previous_hash": null,
            "entries": 3,
            "size_bytes": 347778,
            "last_updated": "2025-11-06T18:20:15Z"
          },
          "macos": {
            "current_hash": "a362bf2bc7dae315052e374aeefb99bcc8642930eed7bbcb8272a05ba6915ac1",
            "previous_hash": null,
            "entries": 5,
            "size_bytes": 347778,
            "last_updated": "2025-11-06T18:20:15Z"
          },
          "safari": {
            "current_hash": "992ee66f36335f6a02514a42390b3053cf8080cc5874430346dfb31c844b4864",
            "previous_hash": null,
            "entries": 3,
            "size_bytes": 347778,
            "last_updated": "2025-11-06T18:20:15Z"
          },
          "tvos": {
            "current_hash": "cf3caac11b331077d646ea700fcfb6950063f62d6470691b00803de8f37c892d",
            "previous_hash": null,
            "entries": 2,
            "size_bytes": 347778,
            "last_updated": "2025-11-06T18:20:15Z"
          },
          "visionos": {
            "current_hash": "4300cb1233d156d935b30b527cc7cdf5982ff2e4420cc8689fd0b539e088d354",
            "previous_hash": null,
            "entries": 3,
            "size_bytes": 347778,
            "last_updated": "2025-11-06T18:20:15Z"
          },
          "watchos": {
            "current_hash": "ef831580512bf9e206da915a7c0efa0371786243667c0eca7c0a7a82f2bfa254",
            "previous_hash": null,
            "entries": 2,
            "size_bytes": 347778,
            "last_updated": "2025-11-06T18:20:15Z"
          }
        }
      }
    },
    "bulletin": {
      "last_run": "2025-11-06T18:20:16Z",
      "bulletin_count": 1,
      "cve_count": 135,
      "status": "completed",
      "current_hash": "9da7e46dad2a8826da36866ed11e49d90f18f8176741835f61c4760e3305dfe9",
      "previous_hash": "14be532e622fb548b696ead83b23ed3c1e895eaf857fa0f00d519bff70a8afc7",
      "live_check_enabled": false
    },
    "enrich": null
  }
}